{
  "id": "ff5aa651-db1d-4da7-995f-6ea1ccf5e98d",
  "prevId": "b7176257-5fea-4dd2-988c-19f98226e49c",
  "version": "7",
  "dialect": "postgresql",
  "tables": {
    "public.applications": {
      "name": "applications",
      "schema": "",
      "columns": {
        "id": {
          "name": "id",
          "type": "uuid",
          "primaryKey": true,
          "notNull": true,
          "default": "gen_random_uuid()"
        },
        "company_id": {
          "name": "company_id",
          "type": "uuid",
          "primaryKey": false,
          "notNull": true
        },
        "title": {
          "name": "title",
          "type": "text",
          "primaryKey": false,
          "notNull": true
        },
        "stage": {
          "name": "stage",
          "type": "stage",
          "typeSchema": "public",
          "primaryKey": false,
          "notNull": true,
          "default": "'applied'"
        },
        "outcome": {
          "name": "outcome",
          "type": "outcome",
          "typeSchema": "public",
          "primaryKey": false,
          "notNull": true,
          "default": "'in_progress'"
        },
        "applied_at": {
          "name": "applied_at",
          "type": "timestamp with time zone",
          "primaryKey": false,
          "notNull": true,
          "default": "now()"
        },
        "closed_at": {
          "name": "closed_at",
          "type": "timestamp with time zone",
          "primaryKey": false,
          "notNull": false
        },
        "created_at": {
          "name": "created_at",
          "type": "timestamp with time zone",
          "primaryKey": false,
          "notNull": true,
          "default": "now()"
        },
        "updated_at": {
          "name": "updated_at",
          "type": "timestamp with time zone",
          "primaryKey": false,
          "notNull": true,
          "default": "now()"
        }
      },
      "indexes": {
        "applications_company_id_idx": {
          "name": "applications_company_id_idx",
          "columns": [
            {
              "expression": "company_id",
              "isExpression": false,
              "asc": true,
              "nulls": "last"
            }
          ],
          "isUnique": false,
          "concurrently": false,
          "method": "btree",
          "with": {}
        }
      },
      "foreignKeys": {
        "applications_company_id_companies_id_fk": {
          "name": "applications_company_id_companies_id_fk",
          "tableFrom": "applications",
          "tableTo": "companies",
          "columnsFrom": ["company_id"],
          "columnsTo": ["id"],
          "onDelete": "no action",
          "onUpdate": "no action"
        }
      },
      "compositePrimaryKeys": {},
      "uniqueConstraints": {},
      "policies": {},
      "checkConstraints": {
        "applications_closed_iff_ended": {
          "name": "applications_closed_iff_ended",
          "value": "(\"applications\".\"outcome\" = 'in_progress') = (\"applications\".\"closed_at\" IS NULL)"
        }
      },
      "isRLSEnabled": true
    },
    "public.companies": {
      "name": "companies",
      "schema": "",
      "columns": {
        "id": {
          "name": "id",
          "type": "uuid",
          "primaryKey": true,
          "notNull": true,
          "default": "gen_random_uuid()"
        },
        "name": {
          "name": "name",
          "type": "text",
          "primaryKey": false,
          "notNull": true
        },
        "memo": {
          "name": "memo",
          "type": "text",
          "primaryKey": false,
          "notNull": false
        },
        "created_at": {
          "name": "created_at",
          "type": "timestamp with time zone",
          "primaryKey": false,
          "notNull": true,
          "default": "now()"
        }
      },
      "indexes": {},
      "foreignKeys": {},
      "compositePrimaryKeys": {},
      "uniqueConstraints": {
        "companies_name_unique": {
          "name": "companies_name_unique",
          "nullsNotDistinct": false,
          "columns": ["name"]
        }
      },
      "policies": {},
      "checkConstraints": {},
      "isRLSEnabled": true
    },
    "public.posting_snapshots": {
      "name": "posting_snapshots",
      "schema": "",
      "columns": {
        "id": {
          "name": "id",
          "type": "uuid",
          "primaryKey": true,
          "notNull": true,
          "default": "gen_random_uuid()"
        },
        "application_id": {
          "name": "application_id",
          "type": "uuid",
          "primaryKey": false,
          "notNull": true
        },
        "content": {
          "name": "content",
          "type": "text",
          "primaryKey": false,
          "notNull": true
        },
        "source_url": {
          "name": "source_url",
          "type": "text",
          "primaryKey": false,
          "notNull": false
        },
        "captured_at": {
          "name": "captured_at",
          "type": "timestamp with time zone",
          "primaryKey": false,
          "notNull": true,
          "default": "now()"
        },
        "updated_at": {
          "name": "updated_at",
          "type": "timestamp with time zone",
          "primaryKey": false,
          "notNull": true,
          "default": "now()"
        }
      },
      "indexes": {},
      "foreignKeys": {
        "posting_snapshots_application_id_applications_id_fk": {
          "name": "posting_snapshots_application_id_applications_id_fk",
          "tableFrom": "posting_snapshots",
          "tableTo": "applications",
          "columnsFrom": ["application_id"],
          "columnsTo": ["id"],
          "onDelete": "cascade",
          "onUpdate": "no action"
        }
      },
      "compositePrimaryKeys": {},
      "uniqueConstraints": {
        "posting_snapshots_application_id_unique": {
          "name": "posting_snapshots_application_id_unique",
          "nullsNotDistinct": false,
          "columns": ["application_id"]
        }
      },
      "policies": {},
      "checkConstraints": {},
      "isRLSEnabled": true
    },
    "public.stage_transitions": {
      "name": "stage_transitions",
      "schema": "",
      "columns": {
        "id": {
          "name": "id",
          "type": "uuid",
          "primaryKey": true,
          "notNull": true,
          "default": "gen_random_uuid()"
        },
        "application_id": {
          "name": "application_id",
          "type": "uuid",
          "primaryKey": false,
          "notNull": true
        },
        "from_stage": {
          "name": "from_stage",
          "type": "stage",
          "typeSchema": "public",
          "primaryKey": false,
          "notNull": false
        },
        "to_stage": {
          "name": "to_stage",
          "type": "stage",
          "typeSchema": "public",
          "primaryKey": false,
          "notNull": true
        },
        "occurred_at": {
          "name": "occurred_at",
          "type": "timestamp with time zone",
          "primaryKey": false,
          "notNull": true,
          "default": "now()"
        }
      },
      "indexes": {
        "stage_transitions_application_id_idx": {
          "name": "stage_transitions_application_id_idx",
          "columns": [
            {
              "expression": "application_id",
              "isExpression": false,
              "asc": true,
              "nulls": "last"
            }
          ],
          "isUnique": false,
          "concurrently": false,
          "method": "btree",
          "with": {}
        }
      },
      "foreignKeys": {
        "stage_transitions_application_id_applications_id_fk": {
          "name": "stage_transitions_application_id_applications_id_fk",
          "tableFrom": "stage_transitions",
          "tableTo": "applications",
          "columnsFrom": ["application_id"],
          "columnsTo": ["id"],
          "onDelete": "cascade",
          "onUpdate": "no action"
        }
      },
      "compositePrimaryKeys": {},
      "uniqueConstraints": {},
      "policies": {},
      "checkConstraints": {
        "stage_transitions_stage_changed": {
          "name": "stage_transitions_stage_changed",
          "value": "\"stage_transitions\".\"from_stage\" IS DISTINCT FROM \"stage_transitions\".\"to_stage\""
        }
      },
      "isRLSEnabled": true
    }
  },
  "enums": {
    "public.outcome": {
      "name": "outcome",
      "schema": "public",
      "values": ["in_progress", "rejected", "withdrawn", "accepted"]
    },
    "public.stage": {
      "name": "stage",
      "schema": "public",
      "values": ["applied", "screening", "assignment", "interview", "offer"]
    }
  },
  "schemas": {},
  "sequences": {},
  "roles": {},
  "policies": {},
  "views": {},
  "_meta": {
    "columns": {},
    "schemas": {},
    "tables": {}
  }
}
